face_lensing/__init__.py
face_lensing/__main__.py
face_lensing/dpl_xy_z1_elliptical.npz
face_lensing-0.5.dist-info/LICENSE
face_lensing-0.5.dist-info/METADATA
face_lensing-0.5.dist-info/WHEEL
face_lensing-0.5.dist-info/entry_points.txt
face_lensing-0.5.dist-info/top_level.txt
face_lensing-0.5.dist-info/RECORD
