Metadata-Version: 2.1
Name: face-lensing
Version: 0.5
Summary: Your face through a gravitational lens
Home-page: https://github.com/aboucaud/face_lensing
Author: Alexandre Boucaud
Author-email: aboucaud@apc.in2p3.fr
License: MIT
Project-URL: Bug Tracker, https://github.com/aboucaud/face_lensing/issues
Platform: any
Classifier: Development Status :: 4 - Beta
Classifier: Intended Audience :: Science/Research
Classifier: Intended Audience :: Education
Classifier: License :: OSI Approved :: MIT License
Classifier: Operating System :: OS Independent
Classifier: Programming Language :: Python :: 3.8
Classifier: Programming Language :: Python :: 3.9
Classifier: Programming Language :: Python :: 3.10
Classifier: Programming Language :: Python :: 3.11
Classifier: Topic :: Scientific/Engineering :: Astronomy
Classifier: Topic :: Scientific/Engineering :: Image Processing
Requires-Python: >=3.8
License-File: LICENSE
Requires-Dist: numpy
Requires-Dist: scipy
Requires-Dist: opencv-python
